CONTRIBUTING.md
DESCRIPTION
LICENSE
MANIFEST.in
README.md
VERSIONS.md
setup.py
PyReact.egg-info/PKG-INFO
PyReact.egg-info/SOURCES.txt
PyReact.egg-info/dependency_links.txt
PyReact.egg-info/requires.txt
PyReact.egg-info/top_level.txt
react/__init__.py
react/jsx.py
react/source.py
react/js/react/JSXTransformer.js
react/js/react/react-with-addons.js
react/js/react/react-with-addons.min.js
react/js/react/react.js
react/js/react/react.min.js
react/test/__init__.py
react/test/__main__.py
react/test/jsx.py
react/test/source.py
react/test/files/test.js
react/utils/__init__.py
react/utils/pipeline.py