Metadata-Version: 1.1
Name: PyReact
Version: 0.6.0
Summary: Python bridge to JSX & the React JavaScript library.
Home-page: https://github.com/reactjs/react-python/
Author: Kunal Mehta
Author-email: kunalm@fb.com
License: Apache-2.0
Platform: UNKNOWN
Classifier: Development Status :: 4 - Beta
Classifier: Intended Audience :: Developers
Classifier: License :: OSI Approved :: Apache Software License
Classifier: Programming Language :: Python
Classifier: Programming Language :: Python :: 2.7
Classifier: Topic :: Software Development :: Code Generators
Classifier: Topic :: Software Development :: Libraries :: Python Modules
